Metadata-Version: 1.0
Name: danniexPipTest
Version: 1.1
Summary: just a test package
Home-page: UNKNOWN
Author: xiongdanni
Author-email: xpanda2518@gmail.com
License: MIT Licence
Keywords: test,client
Platform: UNKNOWN
